cli/__init__.py
cli/cli_main.py
cli/descriptions.py
cli/utils.py
cli/analytics/__init__.py
cli/analytics/feature_selection.py
cli/analytics/principal_component_analysis.py
cli/encryption/__init__.py
cli/encryption/encryption.py
cli/encryption/model_encryption.py
py4phi/__init__.py
py4phi/config_processor.py
py4phi/consts.py
py4phi/controller.py
py4phi/core.py
py4phi/log4j.properties
py4phi/logger_setup.py
py4phi/utils.py
py4phi/_encryption/__init__.py
py4phi/_encryption/_encryptor.py
py4phi/_encryption/_model_encryptor.py
py4phi/_encryption/_pandas_encryptor.py
py4phi/_encryption/_polars_encryptor.py
py4phi/_encryption/_pyspark_encryptor.py
py4phi/analytics/__init__.py
py4phi/analytics/base_analytics.py
py4phi/analytics/feature_selection.py
py4phi/analytics/principal_component_analysis.py
py4phi/dataset_handlers/__init__.py
py4phi/dataset_handlers/base_dataset_handler.py
py4phi/dataset_handlers/pandas_dataset_handler.py
py4phi/dataset_handlers/polars_dataset_handler.py
py4phi/dataset_handlers/pyspark_dataset_handler.py
py4phi/dataset_handlers/pyspark_write_utils.py
py4phi-1.0.0.dist-info/LICENSE
py4phi-1.0.0.dist-info/METADATA
py4phi-1.0.0.dist-info/NOTICE
py4phi-1.0.0.dist-info/WHEEL
py4phi-1.0.0.dist-info/entry_points.txt
py4phi-1.0.0.dist-info/top_level.txt
py4phi-1.0.0.dist-info/RECORD
