Metadata-Version: 2.1
Name: py4phi
Version: 1.0.0
Summary: A library for encryption/decryption and analysis of sensitive data.
Author-email: Volodymyr Kiriushyn <zalorderon3331@gmail.com>
License: Apache License
Project-URL: repository, https://github.com/volodymyrkir/py4phi
Classifier: Development Status :: 5 - Production/Stable
Classifier: License :: OSI Approved :: Apache Software License
Classifier: Programming Language :: Python
Classifier: Programming Language :: Python :: 3.10
Classifier: Programming Language :: Python :: 3.11
Classifier: Programming Language :: Python :: 3.12
Classifier: Intended Audience :: Developers
Classifier: Intended Audience :: Science/Research
Classifier: Intended Audience :: Healthcare Industry
Classifier: Topic :: Security
Classifier: Topic :: Scientific/Engineering
Classifier: Topic :: Scientific/Engineering :: Information Analysis
Classifier: Environment :: Console
Requires-Python: >=3.10
License-File: LICENSE
License-File: NOTICE
Requires-Dist: iniconfig >=2.0.0
Requires-Dist: packaging >=23.2
Requires-Dist: pluggy >=1.3.0
Requires-Dist: py4j >=0.10.9.7
Requires-Dist: pyspark >=3.5.0
Requires-Dist: configparser-crypt >=1.1.0
Requires-Dist: pycryptodome >=3.20.0
Requires-Dist: pandas >=2.2.0
Requires-Dist: pyarrow >=15.0.0
Requires-Dist: polars >=0.20.9
Requires-Dist: click >=8.1.7
Requires-Dist: scikit-learn >=1.4.1.post1
Requires-Dist: scipy >=1.12.0
Requires-Dist: setuptools >=69.1.0
Provides-Extra: test
Requires-Dist: pytest ==7.4.4 ; extra == 'test'
Requires-Dist: pytest-mock ==3.12.0 ; extra == 'test'
Requires-Dist: pytest-cov ==4.1.0 ; extra == 'test'
Requires-Dist: mypy ==1.8.0 ; extra == 'test'
Requires-Dist: ruff ==0.1.3 ; extra == 'test'
